odoo/addons/stock_picking_type_shipping_policy_group_by/README.rst
odoo/addons/stock_picking_type_shipping_policy_group_by/__init__.py
odoo/addons/stock_picking_type_shipping_policy_group_by/__manifest__.py
odoo/addons/stock_picking_type_shipping_policy_group_by/i18n/es_AR.po
odoo/addons/stock_picking_type_shipping_policy_group_by/i18n/it.po
odoo/addons/stock_picking_type_shipping_policy_group_by/i18n/stock_picking_type_shipping_policy_group_by.pot
odoo/addons/stock_picking_type_shipping_policy_group_by/models/__init__.py
odoo/addons/stock_picking_type_shipping_policy_group_by/models/stock_move.py
odoo/addons/stock_picking_type_shipping_policy_group_by/readme/CONTRIBUTORS.rst
odoo/addons/stock_picking_type_shipping_policy_group_by/readme/CREDITS.rst
odoo/addons/stock_picking_type_shipping_policy_group_by/readme/DESCRIPTION.rst
odoo/addons/stock_picking_type_shipping_policy_group_by/static/description/icon.png
odoo/addons/stock_picking_type_shipping_policy_group_by/static/description/index.html
odoo/addons/stock_picking_type_shipping_policy_group_by/tests/__init__.py
odoo/addons/stock_picking_type_shipping_policy_group_by/tests/test_stock_picking_type_shipping_policy.py
odoo14_addon_stock_picking_type_shipping_policy_group_by-14.0.1.0.1.dev6.dist-info/METADATA
odoo14_addon_stock_picking_type_shipping_policy_group_by-14.0.1.0.1.dev6.dist-info/WHEEL
odoo14_addon_stock_picking_type_shipping_policy_group_by-14.0.1.0.1.dev6.dist-info/top_level.txt
odoo14_addon_stock_picking_type_shipping_policy_group_by-14.0.1.0.1.dev6.dist-info/RECORD
