Metadata-Version: 2.1
Name: odoo14-addon-stock-picking-type-shipping-policy-group-by
Version: 14.0.1.0.1.dev6
Summary: Glue module for Picking Type Shipping Policy and Group Transfers by Partner and Carrier
Home-page: https://github.com/OCA/wms
Author: Camptocamp, Odoo Community Association (OCA)
Author-email: support@odoo-community.org
License: AGPL-3
Platform: UNKNOWN
Classifier: Programming Language :: Python
Classifier: Framework :: Odoo
Classifier: Framework :: Odoo :: 14.0
Classifier: License :: OSI Approved :: GNU Affero General Public License v3
Requires-Python: >=3.6
Requires-Dist: odoo14-addon-stock-picking-group-by-partner-by-carrier
Requires-Dist: odoo14-addon-stock-picking-type-shipping-policy
Requires-Dist: odoo <14.1dev,>=14.0a
